apathetic_testing/__init__.py
apathetic_testing/__init__.pyi
apathetic_testing/constants.py
apathetic_testing/fixtures.py
apathetic_testing/logging.py
apathetic_testing/mock.py
apathetic_testing/namespace.py
apathetic_testing/patch.py
apathetic_testing/py.typed
apathetic_testing/pytest.py
apathetic_testing/runtime.py
pytest_apathetic_logging/__init__.py
pytest_apathetic_logging/py.typed
pytest_debug/__init__.py
pytest_debug/plugin.py
pytest_debug/py.typed
pytest_quiet/__init__.py
pytest_quiet/plugin.py
pytest_quiet/py.typed
pytest_runtime/__init__.py
pytest_runtime/plugin.py
pytest_runtime/py.typed
pytest_timeout_defaults/__init__.py
pytest_timeout_defaults/plugin.py
pytest_timeout_defaults/py.typed
pytest_xdist_quiet/__init__.py
pytest_xdist_quiet/plugin.py
pytest_xdist_quiet/py.typed
apathetic_testing-0.3.0.dist-info/METADATA
apathetic_testing-0.3.0.dist-info/WHEEL
apathetic_testing-0.3.0.dist-info/entry_points.txt
apathetic_testing-0.3.0.dist-info/licenses/LICENSE
apathetic_testing-0.3.0.dist-info/RECORD
