Metadata-Version: 2.4
Name: apathetic-testing
Version: 0.3.0
Summary: Runtime-aware pytest extensions. 
License-File: LICENSE
Keywords: library,utilities,utils
Author: Apathetic Tools
Requires-Python: >=3.10
Classifier: Development Status :: 3 - Alpha
Classifier: Intended Audience :: Developers
Classifier: Operating System :: OS Independent
Classifier: Programming Language :: Python :: 3
Classifier: Programming Language :: Python :: 3 :: Only
Classifier: Programming Language :: Python :: 3.10
Classifier: Programming Language :: Python :: 3.11
Classifier: Programming Language :: Python :: 3.12
Classifier: Programming Language :: Python :: 3.13
Classifier: Programming Language :: Python :: 3.14
Classifier: Topic :: Software Development :: Libraries :: Python Modules
Classifier: Topic :: Software Development :: Testing
Classifier: Topic :: Utilities
Requires-Dist: apathetic-logging (>=0.3.2)
Requires-Dist: apathetic-utils (>=0.5.2)
Requires-Dist: pytest (>=9.0.0)
Requires-Dist: pytest-benchmark (>=5.1.0)
Requires-Dist: pytest-cov (>=7.0.0)
Requires-Dist: pytest-dependency (>=0.6.0)
Requires-Dist: pytest-timeout (>=2.4.0)
Requires-Dist: pytest-xdist (>=3.8.0)
Project-URL: Changelog, https://github.com/apathetic-tools/python-testing/releases
Project-URL: Documentation, https://apathetic-tools.github.io/python-testing/
Project-URL: Homepage, https://github.com/apathetic-tools/python-testing
Project-URL: Issues, https://github.com/apathetic-tools/python-testing/issues
Project-URL: Repository, https://github.com/apathetic-tools/python-testing
